scurrypy/__init__.py
scurrypy/client.py
scurrypy/config.py
scurrypy/core/__init__.py
scurrypy/core/addon.py
scurrypy/core/error.py
scurrypy/core/events.py
scurrypy/core/gateway.py
scurrypy/core/http.py
scurrypy/core/intents.py
scurrypy/core/model.py
scurrypy/core/permissions.py
scurrypy/events/__init__.py
scurrypy/events/base_event.py
scurrypy/events/channel_events.py
scurrypy/events/event_types.py
scurrypy/events/gateway_events.py
scurrypy/events/guild_events.py
scurrypy/events/integration_events.py
scurrypy/events/interaction_events.py
scurrypy/events/invite_events.py
scurrypy/events/message_events.py
scurrypy/events/reaction_events.py
scurrypy/events/ready_event.py
scurrypy/events/role_events.py
scurrypy/events/thread_events.py
scurrypy/events/user_events.py
scurrypy/models/__init__.py
scurrypy/models/application.py
scurrypy/models/attachment.py
scurrypy/models/channel.py
scurrypy/models/command.py
scurrypy/models/emoji.py
scurrypy/models/guild.py
scurrypy/models/integration.py
scurrypy/models/interaction.py
scurrypy/models/invite.py
scurrypy/models/message.py
scurrypy/models/role.py
scurrypy/models/sticker.py
scurrypy/models/user.py
scurrypy/params/__init__.py
scurrypy/params/bot_emoji.py
scurrypy/params/channel.py
scurrypy/params/command.py
scurrypy/params/guild.py
scurrypy/params/guild_emoji.py
scurrypy/params/message.py
scurrypy/params/user.py
scurrypy/parts/__init__.py
scurrypy/parts/attachment.py
scurrypy/parts/bot_emoji.py
scurrypy/parts/channel.py
scurrypy/parts/command.py
scurrypy/parts/component_types.py
scurrypy/parts/components.py
scurrypy/parts/components_v2.py
scurrypy/parts/embed.py
scurrypy/parts/guild.py
scurrypy/parts/guild_emoji.py
scurrypy/parts/image_data.py
scurrypy/parts/invite.py
scurrypy/parts/message.py
scurrypy/parts/modal.py
scurrypy/parts/role.py
scurrypy/resources/__init__.py
scurrypy/resources/application.py
scurrypy/resources/base_resource.py
scurrypy/resources/bot_emoji.py
scurrypy/resources/channel.py
scurrypy-0.20.0.dist-info/licenses/LICENSE
scurrypy-0.20.0.dist-info/METADATA
scurrypy-0.20.0.dist-info/WHEEL
scurrypy-0.20.0.dist-info/top_level.txt
scurrypy-0.20.0.dist-info/RECORD
