Metadata-Version: 2.4
Name: scurrypy
Version: 0.20.0
Summary: Dataclass-driven Discord API Wrapper in Python
Author: Furmissile
Requires-Python: >=3.10
License-File: LICENSE
Requires-Dist: aiohttp>=3.8.0
Requires-Dist: websockets>=11.0.0
Requires-Dist: aiofiles>=23.0.0
Dynamic: license-file
